loggly_search/__init__.py
loggly_search/__main__.py
loggly_search-0.1.0.dist-info/entry_points.txt
loggly_search-0.1.0.dist-info/WHEEL
loggly_search-0.1.0.dist-info/METADATA
loggly_search-0.1.0.dist-info/RECORD
