Metadata-Version: 2.1
Name: loggly-search
Version: 0.1.0
Summary: A CLI for Loggly search
Author: Andrew Rabert
Author-email: ar@nullsum.net
Requires-Python: >=3.10,<4.0
Classifier: Programming Language :: Python :: 3
Classifier: Programming Language :: Python :: 3.10
Requires-Dist: ConfigArgParse (>=1.5.3,<2.0.0)
Requires-Dist: httpx (>=0.22.0,<0.23.0)
Requires-Dist: yarl (>=1.7.2,<2.0.0)
